cas_reg/__init__.py
cas_reg/pandas_ext.py
cas_reg-0.1.0.dist-info/licenses/LICENSE
cas_reg-0.1.0.dist-info/WHEEL
cas_reg-0.1.0.dist-info/METADATA
cas_reg-0.1.0.dist-info/RECORD
