Metadata-Version: 2.4
Name: cas-reg
Version: 0.1.0
Summary: Implementation of a pydantic BaseModel class for CAS Registry Numbers® (CAS RN®);
Author: Cullen Klein
Author-email: Cullen Klein <jcklein@alumni.iu.edu>
License-Expression: MIT
License-File: LICENSE
Requires-Dist: pydantic>=2.8.2
Requires-Dist: pandas>=2.0.0 ; extra == 'pandas'
Requires-Dist: numpy>=1.24.0 ; extra == 'pandas'
Requires-Python: >=3.11
Project-URL: Issues, https://github.com/drjckl/cas-reg/issues
Project-URL: Repository, https://github.com/drjckl/cas-reg
Provides-Extra: pandas
